real_deepfakes_detect/__init__.py
real_deepfakes_detect/face_recog.py
real_deepfakes_detect/inference.py
real_deepfakes_detect/configs/ffpp_2s_inference.yaml
real_deepfakes_detect/models/__init__.py
real_deepfakes_detect/models/common.py
real_deepfakes_detect/models/dct.py
real_deepfakes_detect/models/distribute_utils.py
real_deepfakes_detect/models/experimental.py
real_deepfakes_detect/models/ops.py
real_deepfakes_detect/models/stil.py
real_deepfakes_detect/models/twostream_patch.py
real_deepfakes_detect/models/x3d.py
real_deepfakes_detect/models/x3d2stream.py
real_deepfakes_detect/models/x3d_hub.py
real_deepfakes_detect/models/yolo.py
real_deepfakes_detect/utils/__init__.py
real_deepfakes_detect/utils/activations.py
real_deepfakes_detect/utils/autoanchor.py
real_deepfakes_detect/utils/datasets.py
real_deepfakes_detect/utils/face_datasets.py
real_deepfakes_detect/utils/general.py
real_deepfakes_detect/utils/google_utils.py
real_deepfakes_detect/utils/infer_utils.py
real_deepfakes_detect/utils/loss.py
real_deepfakes_detect/utils/lr_utils.py
real_deepfakes_detect/utils/metrics.py
real_deepfakes_detect/utils/metrics_yolov5.py
real_deepfakes_detect/utils/plots.py
real_deepfakes_detect/utils/torch_utils.py
real_deepfakes_detect-0.0.7.dist-info/LICENSE
real_deepfakes_detect-0.0.7.dist-info/METADATA
real_deepfakes_detect-0.0.7.dist-info/WHEEL
real_deepfakes_detect-0.0.7.dist-info/entry_points.txt
real_deepfakes_detect-0.0.7.dist-info/top_level.txt
real_deepfakes_detect-0.0.7.dist-info/RECORD
